COPYING.txt
MANIFEST.in
README.rst
setup.cfg
setup.py
corepos/__init__.py
corepos/_version.py
corepos/api.py
corepos/enum.py
corepos/db/__init__.py
corepos/db/model.py
corepos/db/util.py
corepos/db/lane_op/__init__.py
corepos/db/lane_op/model.py
corepos/db/office_arch/__init__.py
corepos/db/office_arch/model.py
corepos/db/office_op/__init__.py
corepos/db/office_op/model.py
corepos/db/office_trans/__init__.py
corepos/db/office_trans/model.py
corepos/db/office_trans_archive/__init__.py
corepos/db/office_trans_archive/model.py
corepos/trans/__init__.py
corepos/trans/db/__init__.py
corepos/trans/db/model.py
pyCOREPOS.egg-info/PKG-INFO
pyCOREPOS.egg-info/SOURCES.txt
pyCOREPOS.egg-info/dependency_links.txt
pyCOREPOS.egg-info/requires.txt
pyCOREPOS.egg-info/top_level.txt